{
    "sidebar":[
        {
            "title": "homepg",
            "action": "pages/home.md"
        },
        {
            "title": "jijij",
            "link": "https://www.w3schools.com/jsref/jsref_return.asp"
        },
        {
            "title": "kukakkk",
            "action": "pages/home.md"
        },
        {
            "title":"progetti",
            "submenu": [
                {
                    "title": "pji",
                    "link": "https://www.w3schools.com/jsref/jsref_return.asp"
                },
                {
                    "title": "pagina2",
                    "action": "pages/pagina2.md"
                },
                {
                    "title": "pagina9",
                    "action": "pages/pagina2.md"
                }
            ]
        },
        {
            "title": "mister",
            "action": "pages/home.md"
        },
        {
            "title":"articoli",
            "submenu": [
                {
                    "title": "pji",
                    "action": "pages/home.md"
                },
                {
                    "title": "pag",
                    "action": "pages/pagina2.md"
                },
                {
                    "title": "pagina9",
                    "action": "pages/pagina2.md"
                }
            ]
        }
    ]
}
